{
    "AX": {
        "error": 0.009266520896673396,
        "error_type": "SEM",
        "filter_outliers_dict": {
            "filter_outliers": true,
            "iterations": 1,
            "std_devs": 2
        },
        "fit": "average",
        "modifier_error": 0.0,
        "modifier_value": 0.0,
        "value": -0.19211614342800845
    },
    "CDD": {
        "error": 7.671668365751483e-06,
        "error_type": "SEM",
        "filter_outliers_dict": {
            "filter_outliers": true,
            "iterations": 1,
            "std_devs": 10
        },
        "fit": "average",
        "modifier_error": 9.949881171956635e-06,
        "modifier_value": 2.235957469287672e-05,
        "value": 3.605624233325934e-05
    },
    "H1": {
        "error": 0.005573793590896349,
        "error_type": "SEM",
        "filter_outliers_dict": {
            "filter_outliers": true,
            "iterations": 1,
            "std_devs": 2
        },
        "fit": "average",
        "modifier_error": 0.0,
        "modifier_value": 0.0,
        "value": 0.0057419553815709476
    },
    "H2": {
        "error": 0.008651273823638252,
        "error_type": "SEM",
        "filter_outliers_dict": {
            "filter_outliers": true,
            "iterations": 1,
            "std_devs": 2
        },
        "fit": "average",
        "modifier_error": 0.0,
        "modifier_value": 0.0,
        "value": 0.01449961592744694
    },
    "L1": {
        "error": 0.0044753038760654545,
        "error_type": "SEM",
        "filter_outliers_dict": {
            "filter_outliers": true,
            "iterations": 1,
            "std_devs": 2
        },
        "fit": "average",
        "modifier_error": 0.0,
        "modifier_value": 0.0,
        "value": 0.06700210919060026
    },
    "L2": {
        "error": 0.004345973112895722,
        "error_type": "SEM",
        "filter_outliers_dict": {
            "filter_outliers": true,
            "iterations": 1,
            "std_devs": 2
        },
        "fit": "average",
        "modifier_error": 0.0,
        "modifier_value": 0.0,
        "value": -0.03260596324537516
    }
}