{
    "Ar36": {
        "error": 0.0002934646040651869,
        "error_type": "SEM",
        "filter_outliers_dict": {
            "filter_outliers": true,
            "iterations": 1,
            "std_devs": 3,
            "use_iqr_filtering": false,
            "use_standard_deviation_filtering": false
        },
        "fit": "linear",
        "fn": 180,
        "include_baseline_error": true,
        "n": 180,
        "outlier_excluded": [],
        "reviewed": true,
        "user_excluded": [],
        "value": 0.014965994103077777
    },
    "Ar37": {
        "error": 0.004751911133714487,
        "error_type": "SEM",
        "filter_outliers_dict": {
            "filter_outliers": true,
            "iterations": 1,
            "std_devs": 3,
            "use_iqr_filtering": false,
            "use_standard_deviation_filtering": false
        },
        "fit": "linear",
        "fn": 179,
        "include_baseline_error": true,
        "n": 180,
        "outlier_excluded": [
            51
        ],
        "reviewed": true,
        "user_excluded": [],
        "value": 0.08703493402870183
    },
    "Ar38": {
        "error": 0.004613101493953566,
        "error_type": "SEM",
        "filter_outliers_dict": {
            "filter_outliers": true,
            "iterations": 1,
            "std_devs": 3,
            "use_iqr_filtering": false,
            "use_standard_deviation_filtering": false
        },
        "fit": "linear",
        "fn": 178,
        "include_baseline_error": true,
        "n": 180,
        "outlier_excluded": [
            0,
            1
        ],
        "reviewed": true,
        "user_excluded": [],
        "value": 0.8068486594985805
    },
    "Ar39": {
        "error": 0.03163052356751316,
        "error_type": "SEM",
        "filter_outliers_dict": {
            "filter_outliers": true,
            "iterations": 1,
            "std_devs": 3,
            "use_iqr_filtering": false,
            "use_standard_deviation_filtering": false
        },
        "fit": "parabolic",
        "fn": 179,
        "include_baseline_error": true,
        "n": 180,
        "outlier_excluded": [
            101
        ],
        "reviewed": true,
        "user_excluded": [],
        "value": 56.44741381210153
    },
    "Ar40": {
        "error": 0.03459350700081769,
        "error_type": "SEM",
        "filter_outliers_dict": {
            "filter_outliers": true,
            "iterations": 1,
            "std_devs": 3,
            "use_iqr_filtering": false,
            "use_standard_deviation_filtering": false
        },
        "fit": "parabolic",
        "fn": 180,
        "include_baseline_error": true,
        "n": 180,
        "outlier_excluded": [],
        "reviewed": true,
        "user_excluded": [],
        "value": 110.71578162047243
    },
    "Ar41": {
        "error": 0.003915208103183135,
        "error_type": "SEM",
        "filter_outliers_dict": {
            "filter_outliers": true,
            "iterations": 1,
            "std_devs": 2
        },
        "fit": "average",
        "value": 0.11772997866601757
    }
}